{"QUERY PLAN": [{"Plan": {"Node-Type": "Aggregate", "Strategy": "Sorted", "Startup-Cost": "89608.20", "Total-Cost": "89608.53", "Plan-Rows": "15", "Plan-Width": "26", "Output": {"Item": ["warehouse.w_state", "item.i_item_id", "sum(catalog_sales.cs_sales_price)"]}, "Group-Key": {"Item": ["warehouse.w_state", "item.i_item_id"]}, "Plans": {"Plan": {"Node-Type": "Sort", "Parent-Relationship": "Outer", "Startup-Cost": "89608.20", "Total-Cost": "89608.23", "Plan-Rows": "15", "Plan-Width": "26", "Output": {"Item": ["warehouse.w_state", "item.i_item_id", "catalog_sales.cs_sales_price"]}, "Sort-Key": {"Item": ["warehouse.w_state", "item.i_item_id"]}, "Plans": {"Plan": {"Node-Type": "Nested Loop", "Parent-Relationship": "Outer", "Join-Type": "Inner", "Startup-Cost": "1.03", "Total-Cost": "89607.90", "Plan-Rows": "15", "Plan-Width": "26", "Output": {"Item": ["warehouse.w_state", "item.i_item_id", "catalog_sales.cs_sales_price"]}, "Join-Filter": "(catalog_sales.cs_warehouse_sk = warehouse.w_warehouse_sk)", "Plans": {"Plan": [{"Node-Type": "Seq Scan", "Parent-Relationship": "Outer", "Relation-Name": "warehouse", "Schema": "public", "Alias": "warehouse", "Startup-Cost": "0.00", "Total-Cost": "10.50", "Plan-Rows": "50", "Plan-Width": "7", "Output": {"Item": ["warehouse.w_warehouse_sk", "warehouse.w_warehouse_id", "warehouse.w_warehouse_name", "warehouse.w_warehouse_sq_ft", "warehouse.w_street_number", "warehouse.w_street_name", "warehouse.w_street_type", "warehouse.w_suite_number", "warehouse.w_city", "warehouse.w_county", "warehouse.w_state", "warehouse.w_zip", "warehouse.w_country", "warehouse.w_gmt_offset"]}}, {"Node-Type": "Materialize", "Parent-Relationship": "Inner", "Startup-Cost": "1.03", "Total-Cost": "89586.19", "Plan-Rows": "15", "Plan-Width": "27", "Output": {"Item": ["catalog_sales.cs_sales_price", "catalog_sales.cs_warehouse_sk", "item.i_item_id"]}, "Plans": {"Plan": {"Node-Type": "Nested Loop", "Parent-Relationship": "Outer", "Join-Type": "Inner", "Startup-Cost": "1.03", "Total-Cost": "89586.12", "Plan-Rows": "15", "Plan-Width": "27", "Output": {"Item": ["catalog_sales.cs_sales_price", "catalog_sales.cs_warehouse_sk", "item.i_item_id"]}, "Plans": {"Plan": [{"Node-Type": "Nested Loop", "Parent-Relationship": "Outer", "Join-Type": "Inner", "Startup-Cost": "0.73", "Total-Cost": "88377.71", "Plan-Rows": "3651", "Plan-Width": "14", "Output": {"Item": ["catalog_sales.cs_sales_price", "catalog_sales.cs_item_sk", "catalog_sales.cs_warehouse_sk"]}, "Plans": {"Plan": [{"Node-Type": "Index Scan", "Parent-Relationship": "Outer", "Scan-Direction": "Forward", "Index-Name": "date_dim_d_date_idx", "Relation-Name": "date_dim", "Schema": "public", "Alias": "date_dim", "Startup-Cost": "0.30", "Total-Cost": "26.22", "Plan-Rows": "581", "Plan-Width": "4", "Output": {"Item": ["date_dim.d_date_sk", "date_dim.d_date_id", "date_dim.d_date", "date_dim.d_month_seq", "date_dim.d_week_seq", "date_dim.d_quarter_seq", "date_dim.d_year", "date_dim.d_dow", "date_dim.d_moy", "date_dim.d_dom", "date_dim.d_qoy", "date_dim.d_fy_year", "date_dim.d_fy_quarter_seq", "date_dim.d_fy_week_seq", "date_dim.d_day_name", "date_dim.d_quarter_name", "date_dim.d_holiday", "date_dim.d_weekend", "date_dim.d_following_holiday", "date_dim.d_first_dom", "date_dim.d_last_dom", "date_dim.d_same_day_ly", "date_dim.d_same_day_lq", "date_dim.d_current_day", "date_dim.d_current_week", "date_dim.d_current_month", "date_dim.d_current_quarter", "date_dim.d_current_year"]}, "Index-Cond": "((date_dim.d_date >= '2001-01-17'::date) AND (date_dim.d_date <= '2001-03-17'::date))"}, {"Node-Type": "Index Scan", "Parent-Relationship": "Inner", "Scan-Direction": "Forward", "Index-Name": "catalog_sales_cs_sold_date_sk_idx", "Relation-Name": "catalog_sales", "Schema": "public", "Alias": "catalog_sales", "Startup-Cost": "0.43", "Total-Cost": "126.99", "Plan-Rows": "2508", "Plan-Width": "18", "Output": {"Item": ["catalog_sales.cs_sold_date_sk", "catalog_sales.cs_sold_time_sk", "catalog_sales.cs_ship_date_sk", "catalog_sales.cs_bill_customer_sk", "catalog_sales.cs_bill_cdemo_sk", "catalog_sales.cs_bill_hdemo_sk", "catalog_sales.cs_bill_addr_sk", "catalog_sales.cs_ship_customer_sk", "catalog_sales.cs_ship_cdemo_sk", "catalog_sales.cs_ship_hdemo_sk", "catalog_sales.cs_ship_addr_sk", "catalog_sales.cs_call_center_sk", "catalog_sales.cs_catalog_page_sk", "catalog_sales.cs_ship_mode_sk", "catalog_sales.cs_warehouse_sk", "catalog_sales.cs_item_sk", "catalog_sales.cs_promo_sk", "catalog_sales.cs_order_number", "catalog_sales.cs_quantity", "catalog_sales.cs_wholesale_cost", "catalog_sales.cs_list_price", "catalog_sales.cs_sales_price", "catalog_sales.cs_ext_discount_amt", "catalog_sales.cs_ext_sales_price", "catalog_sales.cs_ext_wholesale_cost", "catalog_sales.cs_ext_list_price", "catalog_sales.cs_ext_tax", "catalog_sales.cs_coupon_amt", "catalog_sales.cs_ext_ship_cost", "catalog_sales.cs_net_paid", "catalog_sales.cs_net_paid_inc_tax", "catalog_sales.cs_net_paid_inc_ship", "catalog_sales.cs_net_paid_inc_ship_tax", "catalog_sales.cs_net_profit"]}, "Index-Cond": "(catalog_sales.cs_sold_date_sk = date_dim.d_date_sk)"}]}}, {"Node-Type": "Index Scan", "Parent-Relationship": "Inner", "Scan-Direction": "Forward", "Index-Name": "item_pkey", "Relation-Name": "item", "Schema": "public", "Alias": "item", "Startup-Cost": "0.29", "Total-Cost": "0.32", "Plan-Rows": "1", "Plan-Width": "21", "Output": {"Item": ["item.i_item_sk", "item.i_item_id", "item.i_rec_start_date", "item.i_rec_end_date", "item.i_item_desc", "item.i_current_price", "item.i_wholesale_cost", "item.i_brand_id", "item.i_brand", "item.i_class_id", "item.i_class", "item.i_category_id", "item.i_category", "item.i_manufact_id", "item.i_manufact", "item.i_size", "item.i_formulation", "item.i_color", "item.i_units", "item.i_container", "item.i_manager_id", "item.i_product_name"]}, "Index-Cond": "(item.i_item_sk = catalog_sales.cs_item_sk)", "Filter": "((item.i_current_price >= 0.99) AND (item.i_current_price <= 1.49))"}]}}}}]}}}}}}}]}